dotlab/__init__.py
dotlab/balancing.py
dotlab/data_analysis.py
dotlab_lib-1.1.0.dist-info/METADATA
dotlab_lib-1.1.0.dist-info/WHEEL
dotlab_lib-1.1.0.dist-info/top_level.txt
dotlab_lib-1.1.0.dist-info/RECORD
