Metadata-Version: 2.1
Name: dotlab-lib
Version: 1.1.0
Summary: DotLAB Library
Author: DotLAB Brazil
Author-email: igorviort@gmail.com
License: MIT
Requires-Dist: pandas
